mezzanine2jekyll/__init__.py
mezzanine2jekyll/management/__init__.py
mezzanine2jekyll/management/commands/__init__.py
mezzanine2jekyll/management/commands/mezzanine2jekyll.py
mezzanine2jekyll-1.0.1.dist-info/DESCRIPTION.rst
mezzanine2jekyll-1.0.1.dist-info/METADATA
mezzanine2jekyll-1.0.1.dist-info/RECORD
mezzanine2jekyll-1.0.1.dist-info/WHEEL
mezzanine2jekyll-1.0.1.dist-info/metadata.json
mezzanine2jekyll-1.0.1.dist-info/top_level.txt
