Metadata-Version: 2.0
Name: mezzanine2jekyll
Version: 1.0.1
Summary: Django management command to add support for exporting Mezzanine's blog posts to Jekyll post files
Home-page: https://github.com/sjkingo/mezzanine2jekyll
Author: Sam Kingston
Author-email: sam@sjkwi.com.au
License: BSD
Platform: UNKNOWN
Classifier: Framework :: Django
Classifier: Intended Audience :: Developers
Classifier: License :: OSI Approved :: BSD License
Classifier: Programming Language :: Python
Classifier: Programming Language :: Python :: 2.7
Classifier: Programming Language :: Python :: 3
Classifier: Programming Language :: Python :: 3.4
Requires-Dist: Mezzanine
